openmldb_server/__init__.py
openmldb_server/server.py
openmldb_server/dist/favicon.ico
openmldb_server/dist/index.html
openmldb_server/dist/lab1.json
openmldb_server/dist/lab2.json
openmldb_server/dist/lab3.json
openmldb_server/dist/css/app.a05ed1da.css
openmldb_server/dist/css/chunk-vendors.a16c4353.css
openmldb_server/dist/fonts/element-icons.535877f5.woff
openmldb_server/dist/fonts/element-icons.732389de.ttf
openmldb_server/dist/js/app.39b8c178.js
openmldb_server/dist/js/app.39b8c178.js.map
openmldb_server/dist/js/chunk-vendors.8a845657.js
openmldb_server/dist/js/chunk-vendors.8a845657.js.map
openmldb_lab-0.1.4.dist-info/LICENSE
openmldb_lab-0.1.4.dist-info/METADATA
openmldb_lab-0.1.4.dist-info/WHEEL
openmldb_lab-0.1.4.dist-info/entry_points.txt
openmldb_lab-0.1.4.dist-info/top_level.txt
openmldb_lab-0.1.4.dist-info/RECORD
